Ddnet/Ddnet.py
Ddnet/TAILab.py
Ddnet/__init__.py
Ddnet-0.0.5.dist-info/LICENSE
Ddnet-0.0.5.dist-info/METADATA
Ddnet-0.0.5.dist-info/WHEEL
Ddnet-0.0.5.dist-info/top_level.txt
Ddnet-0.0.5.dist-info/RECORD
