Metadata-Version: 2.1
Name: Ddnet
Version: 0.0.5
Summary: This is a test. This project is not very useful!!!
Home-page: https://github.com/Zichuana/Ddnet
Author: Zichuana
Author-email: 2092653757@qq.com
Classifier: Programming Language :: Python :: 3
Classifier: License :: OSI Approved :: MIT License
Classifier: Operating System :: OS Independent
License-File: LICENSE
Requires-Dist: pandas
Requires-Dist: matplotlib
Requires-Dist: numpy
Requires-Dist: scipy
Requires-Dist: pandas-profiling
Requires-Dist: folium
Requires-Dist: seaborn
Requires-Dist: random
Requires-Dist: os
